CHANGES.txt
MANIFEST.in
README.txt
setup.py
MillisecondCounter/__init__.py
MillisecondCounter.egg-info/PKG-INFO
MillisecondCounter.egg-info/SOURCES.txt
MillisecondCounter.egg-info/dependency_links.txt
MillisecondCounter.egg-info/top_level.txt