Metadata-Version: 1.1
Name: MillisecondCounter
Version: 0.0.1
Summary: Python utility class to get execution runtime in milliseconds
Home-page: https://github.com/stuartornum/python-MillisecondCounter
Author: Stuart Munro
Author-email: stuart@munro.co
License: MIT
Platform: Posix; MacOS X
Classifier: Intended Audience :: Developers
Classifier: License :: OSI Approved :: MIT License
Classifier: Topic :: Internet
